﻿<?xml version="1.0" encoding="utf-8"?>
<Return xmlns="http://www.irs.gov/efile" xmlns:xsi="http://www.w3.org/2001/XMLSchema-instance" xsi:schemaLocation="http://www.irs.gov/efile" returnVersion="2017v2.3">
  <ReturnHeader binaryAttachmentCnt="0">
    <ReturnTs>2019-04-11T17:35:54-05:00</ReturnTs>
    <TaxPeriodEndDt>2018-06-30</TaxPeriodEndDt>
    <PreparerFirmGrp>
      <PreparerFirmName>
        <BusinessNameLine1Txt>GARY MCGEE &amp; CO LLP</BusinessNameLine1Txt>
      </PreparerFirmName>
      <PreparerUSAddress>
        <AddressLine1Txt>808 SW THIRD AVENUE SUITE 700</AddressLine1Txt>
        <CityNm>PORTLAND</CityNm>
        <StateAbbreviationCd>OR</StateAbbreviationCd>
        <ZIPCd>97204</ZIPCd>
      </PreparerUSAddress>
    </PreparerFirmGrp>
    <ReturnTypeCd>990</ReturnTypeCd>
    <TaxPeriodBeginDt>2017-07-01</TaxPeriodBeginDt>
    <Filer>
      <EIN>204223437</EIN>
      <BusinessName>
        <BusinessNameLine1Txt>SCHOOLHOUSE SUPPLIES INC</BusinessNameLine1Txt>
      </BusinessName>
      <BusinessNameControlTxt>SCHO</BusinessNameControlTxt>
      <PhoneNum>5032499933</PhoneNum>
      <USAddress>
        <AddressLine1Txt>4916 NE 122ND AVENUE</AddressLine1Txt>
        <CityNm>PORTLAND</CityNm>
        <StateAbbreviationCd>OR</StateAbbreviationCd>
        <ZIPCd>97230</ZIPCd>
      </USAddress>
    </Filer>
    <BusinessOfficerGrp>
      <PersonNm>ALICE FORBES</PersonNm>
      <PersonTitleTxt>EXECUTIVE DIRECTOR</PersonTitleTxt>
      <PhoneNum>5032499933</PhoneNum>
      <SignatureDt>2019-04-11</SignatureDt>
    </BusinessOfficerGrp>
    <PreparerPersonGrp>
      <PreparerPersonNm>GARY MCGEE</PreparerPersonNm>
      <PTIN>P00743279</PTIN>
      <PhoneNum>5032222515</PhoneNum>
    </PreparerPersonGrp>
    <FilingSecurityInformation>
      <IPAddress>
        <IPv4AddressTxt>96.95.137.101</IPv4AddressTxt>
      </IPAddress>
      <IPDt>2019-04-11</IPDt>
      <IPTm>15:35:19</IPTm>
      <IPTimezoneCd>PD</IPTimezoneCd>
      <FilingLicenseTypeCd>P</FilingLicenseTypeCd>
      <AtSubmissionCreationDeviceId>A6C5305D582DC7D0F7638E9F545A4A195DA351B5</AtSubmissionCreationDeviceId>
      <AtSubmissionFilingDeviceId>AC9CD49D32C8AABC9324D509F740A6FBFA7110E7</AtSubmissionFilingDeviceId>
    </FilingSecurityInformation>
    <TaxYr>2017</TaxYr>
    <BuildTS>2019-02-21 02:37:17Z</BuildTS>
  </ReturnHeader>
  <ReturnData documentCnt="8">
    <IRS990 documentId="RetDoc1038000001" referenceDocumentId="RetDoc1044400001">
      <AddressChangeInd>X</AddressChangeInd>
      <PrincipalOfficerNm>ALICE FORBES</PrincipalOfficerNm>
      <USAddress>
        <AddressLine1Txt>4916 NE 122ND AVENUE</AddressLine1Txt>
        <CityNm>PORTLAND</CityNm>
        <StateAbbreviationCd>OR</StateAbbreviationCd>
        <ZIPCd>97230</ZIPCd>
      </USAddress>
      <GrossReceiptsAmt>4058503</GrossReceiptsAmt>
      <GroupReturnForAffiliatesInd>0</GroupReturnForAffiliatesInd>
      <Organization501c3Ind>X</Organization501c3Ind>
      <WebsiteAddressTxt>WWW.SCHOOLHOUSESUPPLIES.ORG</WebsiteAddressTxt>
      <TypeOfOrganizationCorpInd>X</TypeOfOrganizationCorpInd>
      <FormationYr>2006</FormationYr>
      <LegalDomicileStateCd>OR</LegalDomicileStateCd>
      <ActivityOrMissionDesc>TO SERVE CLASSROOMS IN NEED BY OPERATING A VOLUNTEER-RUN FREE STORE FOR TEACHERS.SINCE OPENING OUR DOORS IN 1999, OUR MISSION REMAINS THE SAME: TO SUPPORT PUBLIC EDUCATION IN THE PORTLAND AREA BY PROVIDING FREE SCHOOL SUPPLIES TO STUDENTS IN NEED. WE DO THIS BECAUSE WE BELIEVE THAT EVERY CHILD DESERVES SCHOOL SUPPLIES AND HAS THE RIGHT TO A QUALITY EDUCATION REGARDLESS OF THEIR FAMILY'S INCOME OR RACIAL/ETHNIC IDENTITY. OUR ULTIMATE GOAL IS TO LEVEL THE PLAYING FIELD SO EVERY CHILD HAS ACCESS TO THE TOOLS THAT ALLOW THEM TO ACHIEVE ACADEMIC SUCCESS AND FEEL CONFIDENT. THE PROGRAM DELIVERY MODEL ACHIEVES ADDITIONAL GOALS THROUGH COMMUNITY ENGAGEMENT AND BY KEEPING SUPPLIES OUT OF THE WASTE STREAM. WITH THE COMMUNITY'S SUPPORT, SCHOOLHOUSE SUPPLIES HAS DISTRIBUTED NEARLY $30 MILLION IN FREE SCHOOL SUPPLIES AND BENEFITTED HUNDREDS OF THOUSANDS OF CHILDREN.</ActivityOrMissionDesc>
      <VotingMembersGoverningBodyCnt>8</VotingMembersGoverningBodyCnt>
      <VotingMembersIndependentCnt>8</VotingMembersIndependentCnt>
      <TotalEmployeeCnt>10</TotalEmployeeCnt>
      <TotalVolunteersCnt>948</TotalVolunteersCnt>
      <TotalGrossUBIAmt>0</TotalGrossUBIAmt>
      <NetUnrelatedBusTxblIncmAmt>0</NetUnrelatedBusTxblIncmAmt>
      <PYContributionsGrantsAmt>3244062</PYContributionsGrantsAmt>
      <CYContributionsGrantsAmt>4004999</CYContributionsGrantsAmt>
      <PYProgramServiceRevenueAmt>20374</PYProgramServiceRevenueAmt>
      <CYProgramServiceRevenueAmt>15325</CYProgramServiceRevenueAmt>
      <PYInvestmentIncomeAmt>497</PYInvestmentIncomeAmt>
      <CYInvestmentIncomeAmt>495</CYInvestmentIncomeAmt>
      <PYOtherRevenueAmt>-42869</PYOtherRevenueAmt>
      <CYOtherRevenueAmt>-28796</CYOtherRevenueAmt>
      <PYTotalRevenueAmt>3222064</PYTotalRevenueAmt>
      <CYTotalRevenueAmt>3992023</CYTotalRevenueAmt>
      <PYGrantsAndSimilarPaidAmt>2481828</PYGrantsAndSimilarPaidAmt>
      <CYGrantsAndSimilarPaidAmt>3142149</CYGrantsAndSimilarPaidAmt>
      <PYBenefitsPaidToMembersAmt>0</PYBenefitsPaidToMembersAmt>
      <CYBenefitsPaidToMembersAmt>0</CYBenefitsPaidToMembersAmt>
      <PYSalariesCompEmpBnftPaidAmt>283443</PYSalariesCompEmpBnftPaidAmt>
      <CYSalariesCompEmpBnftPaidAmt>284569</CYSalariesCompEmpBnftPaidAmt>
      <PYTotalProfFndrsngExpnsAmt>3550</PYTotalProfFndrsngExpnsAmt>
      <CYTotalProfFndrsngExpnsAmt>2150</CYTotalProfFndrsngExpnsAmt>
      <CYTotalFundraisingExpenseAmt>119516</CYTotalFundraisingExpenseAmt>
      <PYOtherExpensesAmt>157980</PYOtherExpensesAmt>
      <CYOtherExpensesAmt>127396</CYOtherExpensesAmt>
      <PYTotalExpensesAmt>2926801</PYTotalExpensesAmt>
      <CYTotalExpensesAmt>3556264</CYTotalExpensesAmt>
      <PYRevenuesLessExpensesAmt>295263</PYRevenuesLessExpensesAmt>
      <CYRevenuesLessExpensesAmt>435759</CYRevenuesLessExpensesAmt>
      <TotalAssetsBOYAmt>1033613</TotalAssetsBOYAmt>
      <TotalAssetsEOYAmt>1472878</TotalAssetsEOYAmt>
      <TotalLiabilitiesBOYAmt>16127</TotalLiabilitiesBOYAmt>
      <TotalLiabilitiesEOYAmt>19633</TotalLiabilitiesEOYAmt>
      <NetAssetsOrFundBalancesBOYAmt>1017486</NetAssetsOrFundBalancesBOYAmt>
      <NetAssetsOrFundBalancesEOYAmt>1453245</NetAssetsOrFundBalancesEOYAmt>
      <MissionDesc>TO SUPPORT PUBLIC EDUCATION IN THE PORTLAND AREA BY PROVIDING FREE SCHOOL SUPPLIES TO STUDENTS IN NEED. WE DO THIS BECAUSE WE BELIEVE THAT EVERY CHILD DESERVES SCHOOL SUPPLIES AND HAS THE RIGHT TO A QUALITY EDUCATION REGARDLESS OF CIRCUMSTANCE.</MissionDesc>
      <SignificantNewProgramSrvcInd>0</SignificantNewProgramSrvcInd>
      <SignificantChangeInd>0</SignificantChangeInd>
      <ExpenseAmt>2589093</ExpenseAmt>
      <GrantAmt>2393049</GrantAmt>
      <Desc>THE FREE STORE FOR TEACHERS IS THE CORE OF THE MISSION. SUPPLY DRIVES, COMMUNITY PARTNERSHIPS AND CHARITABLE GIVING KEEP THE SHELVES STOCKED. LAST YEAR, TEACHERS MADE OVER 5,000 SHOPPING TRIPS FOR FREE SUPPLIES AND BENEFITTED APPROXIMATELY 65,000 CHILDREN.</Desc>
      <ProgSrvcAccomActy2Grp>
        <ExpenseAmt>790201</ExpenseAmt>
        <GrantAmt>749100</GrantAmt>
        <Desc>TOOLS FOR SCHOOLS CONNECTS SPONSORS WITH SCHOOLS TO PROVIDE BACKPACKS FILLED WITH SUPPLIES TO SUPPORT AN ENTIRE YEAR OF LEARNING FOR EVERY STUDENT. THIS YEAR, NEARLY 11,000 CHILDREN RECEIVED BACKPACKS.</Desc>
      </ProgSrvcAccomActy2Grp>
      <ProgSrvcAccomActy3Grp>
        <ExpenseAmt>5422</ExpenseAmt>
        <RevenueAmt>15325</RevenueAmt>
        <Desc>SCHOOLHOUSE SUPPLIES ONLINE PROVIDES FAMILIES AT PARTICIPATING SCHOOLS THE OPPORTUNITY TO PURCHASE COMPLETE SCHOOL SUPPLY KITS ONLINE.</Desc>
      </ProgSrvcAccomActy3Grp>
      <TotalProgramServiceExpensesAmt>3384716</TotalProgramServiceExpensesAmt>
      <DescribedInSection501c3Ind referenceDocumentId="RetDoc1039100001">1</DescribedInSection501c3Ind>
      <ScheduleBRequiredInd referenceDocumentId="RetDoc1234500001">1</ScheduleBRequiredInd>
      <PoliticalCampaignActyInd>0</PoliticalCampaignActyInd>
      <LobbyingActivitiesInd>0</LobbyingActivitiesInd>
      <SubjectToProxyTaxInd>0</SubjectToProxyTaxInd>
      <DonorAdvisedFundInd referenceDocumentId="RetDoc1040000001">0</DonorAdvisedFundInd>
      <ConservationEasementsInd referenceDocumentId="RetDoc1040000001">0</ConservationEasementsInd>
      <CollectionsOfArtInd referenceDocumentId="RetDoc1040000001">0</CollectionsOfArtInd>
      <CreditCounselingInd referenceDocumentId="RetDoc1040000001">0</CreditCounselingInd>
      <TempOrPermanentEndowmentsInd referenceDocumentId="RetDoc1040000001">0</TempOrPermanentEndowmentsInd>
      <ReportLandBuildingEquipmentInd referenceDocumentId="RetDoc1040000001">1</ReportLandBuildingEquipmentInd>
      <ReportInvestmentsOtherSecInd referenceDocumentId="RetDoc1040000001">0</ReportInvestmentsOtherSecInd>
      <ReportProgramRelatedInvstInd referenceDocumentId="RetDoc1040000001">0</ReportProgramRelatedInvstInd>
      <ReportOtherAssetsInd referenceDocumentId="RetDoc1040000001">0</ReportOtherAssetsInd>
      <ReportOtherLiabilitiesInd referenceDocumentId="RetDoc1040000001">0</ReportOtherLiabilitiesInd>
      <IncludeFIN48FootnoteInd referenceDocumentId="RetDoc1040000001">0</IncludeFIN48FootnoteInd>
      <IndependentAuditFinclStmtInd referenceDocumentId="RetDoc1040000001">0</IndependentAuditFinclStmtInd>
      <ConsolidatedAuditFinclStmtInd referenceDocumentId="RetDoc1040000001">0</ConsolidatedAuditFinclStmtInd>
      <SchoolOperatingInd>0</SchoolOperatingInd>
      <ForeignOfficeInd>0</ForeignOfficeInd>
      <ForeignActivitiesInd>0</ForeignActivitiesInd>
      <MoreThan5000KToOrgInd>0</MoreThan5000KToOrgInd>
      <MoreThan5000KToIndividualsInd>0</MoreThan5000KToIndividualsInd>
      <ProfessionalFundraisingInd referenceDocumentId="RetDoc1041300001">0</ProfessionalFundraisingInd>
      <FundraisingActivitiesInd referenceDocumentId="RetDoc1041300001">1</FundraisingActivitiesInd>
      <GamingActivitiesInd referenceDocumentId="RetDoc1041300001">0</GamingActivitiesInd>
      <OperateHospitalInd>0</OperateHospitalInd>
      <GrantsToOrganizationsInd referenceDocumentId="RetDoc1041900001">1</GrantsToOrganizationsInd>
      <GrantsToIndividualsInd referenceDocumentId="RetDoc1041900001">0</GrantsToIndividualsInd>
      <ScheduleJRequiredInd>0</ScheduleJRequiredInd>
      <TaxExemptBondsInd>0</TaxExemptBondsInd>
      <EngagedInExcessBenefitTransInd>0</EngagedInExcessBenefitTransInd>
      <PYExcessBenefitTransInd>0</PYExcessBenefitTransInd>
      <LoanOutstandingInd>0</LoanOutstandingInd>
      <GrantToRelatedPersonInd>0</GrantToRelatedPersonInd>
      <BusinessRlnWithOrgMemInd>0</BusinessRlnWithOrgMemInd>
      <BusinessRlnWithFamMemInd>0</BusinessRlnWithFamMemInd>
      <BusinessRlnWithOfficerEntInd>0</BusinessRlnWithOfficerEntInd>
      <DeductibleNonCashContriInd referenceDocumentId="RetDoc1042900001">1</DeductibleNonCashContriInd>
      <DeductibleArtContributionInd referenceDocumentId="RetDoc1042900001">0</DeductibleArtContributionInd>
      <TerminateOperationsInd>0</TerminateOperationsInd>
      <PartialLiquidationInd>0</PartialLiquidationInd>
      <DisregardedEntityInd>0</DisregardedEntityInd>
      <RelatedEntityInd>0</RelatedEntityInd>
      <RelatedOrganizationCtrlEntInd>0</RelatedOrganizationCtrlEntInd>
      <TrnsfrExmptNonChrtblRltdOrgInd>0</TrnsfrExmptNonChrtblRltdOrgInd>
      <ActivitiesConductedPrtshpInd>0</ActivitiesConductedPrtshpInd>
      <ScheduleORequiredInd>1</ScheduleORequiredInd>
      <IRPDocumentCnt>10</IRPDocumentCnt>
      <IRPDocumentW2GCnt>0</IRPDocumentW2GCnt>
      <EmployeeCnt>10</EmployeeCnt>
      <EmploymentTaxReturnsFiledInd>1</EmploymentTaxReturnsFiledInd>
      <UnrelatedBusIncmOverLimitInd>0</UnrelatedBusIncmOverLimitInd>
      <ForeignFinancialAccountInd>0</ForeignFinancialAccountInd>
      <ProhibitedTaxShelterTransInd>0</ProhibitedTaxShelterTransInd>
      <TaxablePartyNotificationInd>0</TaxablePartyNotificationInd>
      <NondeductibleContributionsInd>0</NondeductibleContributionsInd>
      <QuidProQuoContributionsInd>1</QuidProQuoContributionsInd>
      <QuidProQuoContriDisclInd>1</QuidProQuoContriDisclInd>
      <Form8282PropertyDisposedOfInd>0</Form8282PropertyDisposedOfInd>
      <RcvFndsToPayPrsnlBnftCntrctInd>0</RcvFndsToPayPrsnlBnftCntrctInd>
      <PayPremiumsPrsnlBnftCntrctInd>0</PayPremiumsPrsnlBnftCntrctInd>
      <IndoorTanningServicesInd>0</IndoorTanningServicesInd>
      <InfoInScheduleOPartVIInd>X</InfoInScheduleOPartVIInd>
      <GoverningBodyVotingMembersCnt>8</GoverningBodyVotingMembersCnt>
      <IndependentVotingMemberCnt>8</IndependentVotingMemberCnt>
      <FamilyOrBusinessRlnInd>0</FamilyOrBusinessRlnInd>
      <DelegationOfMgmtDutiesInd>0</DelegationOfMgmtDutiesInd>
      <ChangeToOrgDocumentsInd>0</ChangeToOrgDocumentsInd>
      <MaterialDiversionOrMisuseInd>0</MaterialDiversionOrMisuseInd>
      <MembersOrStockholdersInd>0</MembersOrStockholdersInd>
      <ElectionOfBoardMembersInd>0</ElectionOfBoardMembersInd>
      <DecisionsSubjectToApprovaInd>0</DecisionsSubjectToApprovaInd>
      <MinutesOfGoverningBodyInd>1</MinutesOfGoverningBodyInd>
      <MinutesOfCommitteesInd>1</MinutesOfCommitteesInd>
      <OfficerMailingAddressInd>0</OfficerMailingAddressInd>
      <LocalChaptersInd>0</LocalChaptersInd>
      <Form990ProvidedToGvrnBodyInd>1</Form990ProvidedToGvrnBodyInd>
      <ConflictOfInterestPolicyInd>1</ConflictOfInterestPolicyInd>
      <AnnualDisclosureCoveredPrsnInd>1</AnnualDisclosureCoveredPrsnInd>
      <RegularMonitoringEnfrcInd>1</RegularMonitoringEnfrcInd>
      <WhistleblowerPolicyInd>1</WhistleblowerPolicyInd>
      <DocumentRetentionPolicyInd>1</DocumentRetentionPolicyInd>
      <CompensationProcessCEOInd>1</CompensationProcessCEOInd>
      <CompensationProcessOtherInd>0</CompensationProcessOtherInd>
      <InvestmentInJointVentureInd>0</InvestmentInJointVentureInd>
      <StatesWhereCopyOfReturnIsFldCd>OR</StatesWhereCopyOfReturnIsFldCd>
      <UponRequestInd>X</UponRequestInd>
      <BooksInCareOfDetail>
        <BusinessName>
          <BusinessNameLine1Txt>ALICE FORBES</BusinessNameLine1Txt>
        </BusinessName>
        <PhoneNum>5032499933</PhoneNum>
        <USAddress>
          <AddressLine1Txt>4916 NE 122ND AVENUE</AddressLine1Txt>
          <CityNm>PORTLAND</CityNm>
          <StateAbbreviationCd>OR</StateAbbreviationCd>
          <ZIPCd>97230</ZIPCd>
        </USAddress>
      </BooksInCareOfDetail>
      <Form990PartVIISectionAGrp>
        <PersonNm>TONY AMANDI</PersonNm>
        <TitleTxt>BOARD MEMBER</TitleTxt>
        <AverageHoursPerWeekRt>1.00</AverageHoursPerWeekRt>
        <IndividualTrusteeOrDirectorInd>X</IndividualTrusteeOrDirectorInd>
        <ReportableCompFromOrgAmt>0</ReportableCompFromOrgAmt>
        <ReportableCompFromRltdOrgAmt>0</ReportableCompFromRltdOrgAmt>
        <OtherCompensationAmt>0</OtherCompensationAmt>
      </Form990PartVIISectionAGrp>
      <Form990PartVIISectionAGrp>
        <PersonNm>COLE CHATTERTON</PersonNm>
        <TitleTxt>BOARD MEMBER</TitleTxt>
        <AverageHoursPerWeekRt>1.00</AverageHoursPerWeekRt>
        <IndividualTrusteeOrDirectorInd>X</IndividualTrusteeOrDirectorInd>
        <ReportableCompFromOrgAmt>0</ReportableCompFromOrgAmt>
        <ReportableCompFromRltdOrgAmt>0</ReportableCompFromRltdOrgAmt>
        <OtherCompensationAmt>0</OtherCompensationAmt>
      </Form990PartVIISectionAGrp>
      <Form990PartVIISectionAGrp>
        <PersonNm>NANCY CLARK</PersonNm>
        <TitleTxt>BOARD MEMBER</TitleTxt>
        <AverageHoursPerWeekRt>1.00</AverageHoursPerWeekRt>
        <IndividualTrusteeOrDirectorInd>X</IndividualTrusteeOrDirectorInd>
        <ReportableCompFromOrgAmt>0</ReportableCompFromOrgAmt>
        <ReportableCompFromRltdOrgAmt>0</ReportableCompFromRltdOrgAmt>
        <OtherCompensationAmt>0</OtherCompensationAmt>
      </Form990PartVIISectionAGrp>
      <Form990PartVIISectionAGrp>
        <PersonNm>MICHELE CRUSE</PersonNm>
        <TitleTxt>BOARD MEMBER</TitleTxt>
        <AverageHoursPerWeekRt>1.00</AverageHoursPerWeekRt>
        <IndividualTrusteeOrDirectorInd>X</IndividualTrusteeOrDirectorInd>
        <ReportableCompFromOrgAmt>0</ReportableCompFromOrgAmt>
        <ReportableCompFromRltdOrgAmt>0</ReportableCompFromRltdOrgAmt>
        <OtherCompensationAmt>0</OtherCompensationAmt>
      </Form990PartVIISectionAGrp>
      <Form990PartVIISectionAGrp>
        <PersonNm>ALLISON DEVERMAN</PersonNm>
        <TitleTxt>BOARD MEMBER</TitleTxt>
        <AverageHoursPerWeekRt>1.00</AverageHoursPerWeekRt>
        <IndividualTrusteeOrDirectorInd>X</IndividualTrusteeOrDirectorInd>
        <ReportableCompFromOrgAmt>0</ReportableCompFromOrgAmt>
        <ReportableCompFromRltdOrgAmt>0</ReportableCompFromRltdOrgAmt>
        <OtherCompensationAmt>0</OtherCompensationAmt>
      </Form990PartVIISectionAGrp>
      <Form990PartVIISectionAGrp>
        <PersonNm>JESSICA MAKI</PersonNm>
        <TitleTxt>BOARD MEMBER</TitleTxt>
        <AverageHoursPerWeekRt>1.00</AverageHoursPerWeekRt>
        <IndividualTrusteeOrDirectorInd>X</IndividualTrusteeOrDirectorInd>
        <ReportableCompFromOrgAmt>0</ReportableCompFromOrgAmt>
        <ReportableCompFromRltdOrgAmt>0</ReportableCompFromRltdOrgAmt>
        <OtherCompensationAmt>0</OtherCompensationAmt>
      </Form990PartVIISectionAGrp>
      <Form990PartVIISectionAGrp>
        <PersonNm>JEFFREY MAXWELL</PersonNm>
        <TitleTxt>BOARD MEMBER</TitleTxt>
        <AverageHoursPerWeekRt>1.00</AverageHoursPerWeekRt>
        <IndividualTrusteeOrDirectorInd>X</IndividualTrusteeOrDirectorInd>
        <ReportableCompFromOrgAmt>0</ReportableCompFromOrgAmt>
        <ReportableCompFromRltdOrgAmt>0</ReportableCompFromRltdOrgAmt>
        <OtherCompensationAmt>0</OtherCompensationAmt>
      </Form990PartVIISectionAGrp>
      <Form990PartVIISectionAGrp>
        <PersonNm>KELLY SCHWEIGER</PersonNm>
        <TitleTxt>BOARD MEMBER</TitleTxt>
        <AverageHoursPerWeekRt>1.00</AverageHoursPerWeekRt>
        <IndividualTrusteeOrDirectorInd>X</IndividualTrusteeOrDirectorInd>
        <ReportableCompFromOrgAmt>0</ReportableCompFromOrgAmt>
        <ReportableCompFromRltdOrgAmt>0</ReportableCompFromRltdOrgAmt>
        <OtherCompensationAmt>0</OtherCompensationAmt>
      </Form990PartVIISectionAGrp>
      <Form990PartVIISectionAGrp>
        <PersonNm>KATIE TAYLOR</PersonNm>
        <TitleTxt>PRESIDENT</TitleTxt>
        <AverageHoursPerWeekRt>2.00</AverageHoursPerWeekRt>
        <IndividualTrusteeOrDirectorInd>X</IndividualTrusteeOrDirectorInd>
        <OfficerInd>X</OfficerInd>
        <ReportableCompFromOrgAmt>0</ReportableCompFromOrgAmt>
        <ReportableCompFromRltdOrgAmt>0</ReportableCompFromRltdOrgAmt>
        <OtherCompensationAmt>0</OtherCompensationAmt>
      </Form990PartVIISectionAGrp>
      <Form990PartVIISectionAGrp>
        <PersonNm>JENN LYNCH</PersonNm>
        <TitleTxt>VICE PRESIDENT</TitleTxt>
        <AverageHoursPerWeekRt>2.00</AverageHoursPerWeekRt>
        <IndividualTrusteeOrDirectorInd>X</IndividualTrusteeOrDirectorInd>
        <OfficerInd>X</OfficerInd>
        <ReportableCompFromOrgAmt>0</ReportableCompFromOrgAmt>
        <ReportableCompFromRltdOrgAmt>0</ReportableCompFromRltdOrgAmt>
        <OtherCompensationAmt>0</OtherCompensationAmt>
      </Form990PartVIISectionAGrp>
      <Form990PartVIISectionAGrp>
        <PersonNm>BRANT NORQUIST</PersonNm>
        <TitleTxt>SECRETARY</TitleTxt>
        <AverageHoursPerWeekRt>2.00</AverageHoursPerWeekRt>
        <IndividualTrusteeOrDirectorInd>X</IndividualTrusteeOrDirectorInd>
        <OfficerInd>X</OfficerInd>
        <ReportableCompFromOrgAmt>0</ReportableCompFromOrgAmt>
        <ReportableCompFromRltdOrgAmt>0</ReportableCompFromRltdOrgAmt>
        <OtherCompensationAmt>0</OtherCompensationAmt>
      </Form990PartVIISectionAGrp>
      <Form990PartVIISectionAGrp>
        <PersonNm>KENT IKEDA</PersonNm>
        <TitleTxt>TREASURER</TitleTxt>
        <AverageHoursPerWeekRt>2.00</AverageHoursPerWeekRt>
        <IndividualTrusteeOrDirectorInd>X</IndividualTrusteeOrDirectorInd>
        <OfficerInd>X</OfficerInd>
        <ReportableCompFromOrgAmt>0</ReportableCompFromOrgAmt>
        <ReportableCompFromRltdOrgAmt>0</ReportableCompFromRltdOrgAmt>
        <OtherCompensationAmt>0</OtherCompensationAmt>
      </Form990PartVIISectionAGrp>
      <Form990PartVIISectionAGrp>
        <PersonNm>ALICE FORBES</PersonNm>
        <TitleTxt>EXECUTIVE DIRECTOR</TitleTxt>
        <AverageHoursPerWeekRt>40.00</AverageHoursPerWeekRt>
        <OfficerInd>X</OfficerInd>
        <ReportableCompFromOrgAmt>85000</ReportableCompFromOrgAmt>
        <ReportableCompFromRltdOrgAmt>0</ReportableCompFromRltdOrgAmt>
        <OtherCompensationAmt>6168</OtherCompensationAmt>
      </Form990PartVIISectionAGrp>
      <TotalReportableCompFromOrgAmt>85000</TotalReportableCompFromOrgAmt>
      <TotReportableCompRltdOrgAmt>0</TotReportableCompRltdOrgAmt>
      <TotalOtherCompensationAmt>6168</TotalOtherCompensationAmt>
      <IndivRcvdGreaterThan100KCnt>0</IndivRcvdGreaterThan100KCnt>
      <FormerOfcrEmployeesListedInd>0</FormerOfcrEmployeesListedInd>
      <TotalCompGreaterThan150KInd>0</TotalCompGreaterThan150KInd>
      <CompensationFromOtherSrcsInd>0</CompensationFromOtherSrcsInd>
      <CntrctRcvdGreaterThan100KCnt>0</CntrctRcvdGreaterThan100KCnt>
      <FundraisingAmt>131438</FundraisingAmt>
      <GovernmentGrantsAmt>146833</GovernmentGrantsAmt>
      <AllOtherContributionsAmt>3726728</AllOtherContributionsAmt>
      <NoncashContributionsAmt>3359375</NoncashContributionsAmt>
      <TotalContributionsAmt>4004999</TotalContributionsAmt>
      <ProgramServiceRevenueGrp>
        <Desc>SALES AND OTHER</Desc>
        <BusinessCd>454110</BusinessCd>
        <TotalRevenueColumnAmt>15325</TotalRevenueColumnAmt>
        <RelatedOrExemptFuncIncomeAmt>15325</RelatedOrExemptFuncIncomeAmt>
      </ProgramServiceRevenueGrp>
      <TotalProgramServiceRevenueAmt>15325</TotalProgramServiceRevenueAmt>
      <InvestmentIncomeGrp>
        <TotalRevenueColumnAmt>495</TotalRevenueColumnAmt>
        <ExclusionAmt>495</ExclusionAmt>
      </InvestmentIncomeGrp>
      <GrossRentsGrp>
        <RealAmt>1800</RealAmt>
      </GrossRentsGrp>
      <LessRentalExpensesGrp>
        <RealAmt>0</RealAmt>
      </LessRentalExpensesGrp>
      <RentalIncomeOrLossGrp>
        <RealAmt>1800</RealAmt>
      </RentalIncomeOrLossGrp>
      <NetRentalIncomeOrLossGrp>
        <TotalRevenueColumnAmt>1800</TotalRevenueColumnAmt>
        <ExclusionAmt>1800</ExclusionAmt>
      </NetRentalIncomeOrLossGrp>
      <FundraisingGrossIncomeAmt>35884</FundraisingGrossIncomeAmt>
      <ContriRptFundraisingEventAmt>131438</ContriRptFundraisingEventAmt>
      <FundraisingDirectExpensesAmt>66480</FundraisingDirectExpensesAmt>
      <NetIncmFromFundraisingEvtGrp>
        <TotalRevenueColumnAmt>-30596</TotalRevenueColumnAmt>
        <ExclusionAmt>-30596</ExclusionAmt>
      </NetIncmFromFundraisingEvtGrp>
      <TotalRevenueGrp>
        <TotalRevenueColumnAmt>3992023</TotalRevenueColumnAmt>
        <RelatedOrExemptFuncIncomeAmt>15325</RelatedOrExemptFuncIncomeAmt>
        <UnrelatedBusinessRevenueAmt>0</UnrelatedBusinessRevenueAmt>
        <ExclusionAmt>-28301</ExclusionAmt>
      </TotalRevenueGrp>
      <GrantsToDomesticOrgsGrp>
        <TotalAmt>3142149</TotalAmt>
        <ProgramServicesAmt>3142149</ProgramServicesAmt>
      </GrantsToDomesticOrgsGrp>
      <CompCurrentOfcrDirectorsGrp>
        <TotalAmt>97236</TotalAmt>
        <ProgramServicesAmt>26254</ProgramServicesAmt>
        <ManagementAndGeneralAmt>30143</ManagementAndGeneralAmt>
        <FundraisingAmt>40839</FundraisingAmt>
      </CompCurrentOfcrDirectorsGrp>
      <OtherSalariesAndWagesGrp>
        <TotalAmt>147469</TotalAmt>
        <ProgramServicesAmt>103376</ProgramServicesAmt>
        <ManagementAndGeneralAmt>9585</ManagementAndGeneralAmt>
        <FundraisingAmt>34508</FundraisingAmt>
      </OtherSalariesAndWagesGrp>
      <OtherEmployeeBenefitsGrp>
        <TotalAmt>16859</TotalAmt>
        <ProgramServicesAmt>11818</ProgramServicesAmt>
        <ManagementAndGeneralAmt>1096</ManagementAndGeneralAmt>
        <FundraisingAmt>3945</FundraisingAmt>
      </OtherEmployeeBenefitsGrp>
      <PayrollTaxesGrp>
        <TotalAmt>23005</TotalAmt>
        <ProgramServicesAmt>16000</ProgramServicesAmt>
        <ManagementAndGeneralAmt>1509</ManagementAndGeneralAmt>
        <FundraisingAmt>5496</FundraisingAmt>
      </PayrollTaxesGrp>
      <FeesForServicesLegalGrp>
        <TotalAmt>300</TotalAmt>
        <ProgramServicesAmt>300</ProgramServicesAmt>
      </FeesForServicesLegalGrp>
      <FeesForServicesAccountingGrp>
        <TotalAmt>13581</TotalAmt>
        <ProgramServicesAmt>9506</ProgramServicesAmt>
        <ManagementAndGeneralAmt>951</ManagementAndGeneralAmt>
        <FundraisingAmt>3124</FundraisingAmt>
      </FeesForServicesAccountingGrp>
      <FeesForServicesProfFundraising>
        <TotalAmt>2150</TotalAmt>
        <FundraisingAmt>2150</FundraisingAmt>
      </FeesForServicesProfFundraising>
      <FeesForServicesOtherGrp>
        <TotalAmt>6613</TotalAmt>
        <ProgramServicesAmt>4738</ProgramServicesAmt>
        <ManagementAndGeneralAmt>136</ManagementAndGeneralAmt>
        <FundraisingAmt>1739</FundraisingAmt>
      </FeesForServicesOtherGrp>
      <AdvertisingGrp>
        <TotalAmt>18723</TotalAmt>
        <ProgramServicesAmt>14850</ProgramServicesAmt>
        <FundraisingAmt>3873</FundraisingAmt>
      </AdvertisingGrp>
      <OfficeExpensesGrp>
        <TotalAmt>7747</TotalAmt>
        <ProgramServicesAmt>3854</ProgramServicesAmt>
        <ManagementAndGeneralAmt>490</ManagementAndGeneralAmt>
        <FundraisingAmt>3403</FundraisingAmt>
      </OfficeExpensesGrp>
      <InformationTechnologyGrp>
        <TotalAmt>9526</TotalAmt>
        <ProgramServicesAmt>2885</ProgramServicesAmt>
        <ManagementAndGeneralAmt>713</ManagementAndGeneralAmt>
        <FundraisingAmt>5928</FundraisingAmt>
      </InformationTechnologyGrp>
      <OccupancyGrp>
        <TotalAmt>37188</TotalAmt>
        <ProgramServicesAmt>26032</ProgramServicesAmt>
        <ManagementAndGeneralAmt>2603</ManagementAndGeneralAmt>
        <FundraisingAmt>8553</FundraisingAmt>
      </OccupancyGrp>
      <TravelGrp>
        <TotalAmt>1367</TotalAmt>
        <ProgramServicesAmt>1367</ProgramServicesAmt>
      </TravelGrp>
      <ConferencesMeetingsGrp>
        <TotalAmt>817</TotalAmt>
        <ProgramServicesAmt>596</ProgramServicesAmt>
        <ManagementAndGeneralAmt>95</ManagementAndGeneralAmt>
        <FundraisingAmt>126</FundraisingAmt>
      </ConferencesMeetingsGrp>
      <DepreciationDepletionGrp>
        <TotalAmt>14667</TotalAmt>
        <ProgramServicesAmt>10267</ProgramServicesAmt>
        <ManagementAndGeneralAmt>1027</ManagementAndGeneralAmt>
        <FundraisingAmt>3373</FundraisingAmt>
      </DepreciationDepletionGrp>
      <InsuranceGrp>
        <TotalAmt>9422</TotalAmt>
        <ProgramServicesAmt>5266</ProgramServicesAmt>
        <ManagementAndGeneralAmt>3046</ManagementAndGeneralAmt>
        <FundraisingAmt>1110</FundraisingAmt>
      </InsuranceGrp>
      <OtherExpensesGrp>
        <Desc>MISCELLANEOUS</Desc>
        <TotalAmt>7445</TotalAmt>
        <ProgramServicesAmt>5458</ProgramServicesAmt>
        <ManagementAndGeneralAmt>638</ManagementAndGeneralAmt>
        <FundraisingAmt>1349</FundraisingAmt>
      </OtherExpensesGrp>
      <TotalFunctionalExpensesGrp>
        <TotalAmt>3556264</TotalAmt>
        <ProgramServicesAmt>3384716</ProgramServicesAmt>
        <ManagementAndGeneralAmt>52032</ManagementAndGeneralAmt>
        <FundraisingAmt>119516</FundraisingAmt>
      </TotalFunctionalExpensesGrp>
      <CashNonInterestBearingGrp>
        <BOYAmt>154319</BOYAmt>
        <EOYAmt>275502</EOYAmt>
      </CashNonInterestBearingGrp>
      <SavingsAndTempCashInvstGrp>
        <BOYAmt>264540</BOYAmt>
        <EOYAmt>265895</EOYAmt>
      </SavingsAndTempCashInvstGrp>
      <PledgesAndGrantsReceivableGrp>
        <BOYAmt>80800</BOYAmt>
        <EOYAmt>41350</EOYAmt>
      </PledgesAndGrantsReceivableGrp>
      <AccountsReceivableGrp>
        <BOYAmt>11339</BOYAmt>
        <EOYAmt>7449</EOYAmt>
      </AccountsReceivableGrp>
      <InventoriesForSaleOrUseGrp>
        <BOYAmt>462590</BOYAmt>
        <EOYAmt>836239</EOYAmt>
      </InventoriesForSaleOrUseGrp>
      <PrepaidExpensesDefrdChargesGrp>
        <BOYAmt>37688</BOYAmt>
        <EOYAmt>32571</EOYAmt>
      </PrepaidExpensesDefrdChargesGrp>
      <LandBldgEquipCostOrOtherBssAmt>172975</LandBldgEquipCostOrOtherBssAmt>
      <LandBldgEquipAccumDeprecAmt>165306</LandBldgEquipAccumDeprecAmt>
      <LandBldgEquipBasisNetGrp>
        <BOYAmt>22337</BOYAmt>
        <EOYAmt>7669</EOYAmt>
      </LandBldgEquipBasisNetGrp>
      <OtherAssetsTotalGrp>
        <BOYAmt>0</BOYAmt>
        <EOYAmt>6203</EOYAmt>
      </OtherAssetsTotalGrp>
      <TotalAssetsGrp>
        <BOYAmt>1033613</BOYAmt>
        <EOYAmt>1472878</EOYAmt>
      </TotalAssetsGrp>
      <AccountsPayableAccrExpnssGrp>
        <BOYAmt>16127</BOYAmt>
        <EOYAmt>19633</EOYAmt>
      </AccountsPayableAccrExpnssGrp>
      <TotalLiabilitiesGrp>
        <BOYAmt>16127</BOYAmt>
        <EOYAmt>19633</EOYAmt>
      </TotalLiabilitiesGrp>
      <OrganizationFollowsSFAS117Ind>X</OrganizationFollowsSFAS117Ind>
      <UnrestrictedNetAssetsGrp>
        <BOYAmt>785722</BOYAmt>
        <EOYAmt>1257815</EOYAmt>
      </UnrestrictedNetAssetsGrp>
      <TemporarilyRstrNetAssetsGrp>
        <BOYAmt>231764</BOYAmt>
        <EOYAmt>195430</EOYAmt>
      </TemporarilyRstrNetAssetsGrp>
      <TotalNetAssetsFundBalanceGrp>
        <BOYAmt>1017486</BOYAmt>
        <EOYAmt>1453245</EOYAmt>
      </TotalNetAssetsFundBalanceGrp>
      <TotLiabNetAssetsFundBalanceGrp>
        <BOYAmt>1033613</BOYAmt>
        <EOYAmt>1472878</EOYAmt>
      </TotLiabNetAssetsFundBalanceGrp>
      <ReconcilationRevenueExpnssAmt>435759</ReconcilationRevenueExpnssAmt>
      <OtherChangesInNetAssetsAmt>0</OtherChangesInNetAssetsAmt>
      <MethodOfAccountingAccrualInd>X</MethodOfAccountingAccrualInd>
      <AccountantCompileOrReviewInd>0</AccountantCompileOrReviewInd>
      <FSAuditedInd>0</FSAuditedInd>
      <FederalGrantAuditRequiredInd>0</FederalGrantAuditRequiredInd>
    </IRS990>
    <IRS990ScheduleA documentId="RetDoc1039100001">
      <PublicOrganization170Ind>X</PublicOrganization170Ind>
      <GiftsGrantsContriRcvd170Grp>
        <CurrentTaxYearMinus4YearsAmt>2853151</CurrentTaxYearMinus4YearsAmt>
        <CurrentTaxYearMinus3YearsAmt>3696947</CurrentTaxYearMinus3YearsAmt>
        <CurrentTaxYearMinus2YearsAmt>3449123</CurrentTaxYearMinus2YearsAmt>
        <CurrentTaxYearMinus1YearAmt>3244062</CurrentTaxYearMinus1YearAmt>
        <CurrentTaxYearAmt>4004999</CurrentTaxYearAmt>
        <TotalAmt>17248282</TotalAmt>
      </GiftsGrantsContriRcvd170Grp>
      <GovtFurnSrvcFcltsVl170Grp>
        <CurrentTaxYearMinus4YearsAmt>50220</CurrentTaxYearMinus4YearsAmt>
        <CurrentTaxYearMinus3YearsAmt>50220</CurrentTaxYearMinus3YearsAmt>
        <TotalAmt>100440</TotalAmt>
      </GovtFurnSrvcFcltsVl170Grp>
      <TotalCalendarYear170Grp>
        <CurrentTaxYearMinus4YearsAmt>2903371</CurrentTaxYearMinus4YearsAmt>
        <CurrentTaxYearMinus3YearsAmt>3747167</CurrentTaxYearMinus3YearsAmt>
        <CurrentTaxYearMinus2YearsAmt>3449123</CurrentTaxYearMinus2YearsAmt>
        <CurrentTaxYearMinus1YearAmt>3244062</CurrentTaxYearMinus1YearAmt>
        <CurrentTaxYearAmt>4004999</CurrentTaxYearAmt>
        <TotalAmt>17348722</TotalAmt>
      </TotalCalendarYear170Grp>
      <SubstantialContributorsTotAmt>1392843</SubstantialContributorsTotAmt>
      <PublicSupportTotal170Amt>15955879</PublicSupportTotal170Amt>
      <GrossInvestmentIncome170Grp>
        <CurrentTaxYearMinus4YearsAmt>1334</CurrentTaxYearMinus4YearsAmt>
        <CurrentTaxYearMinus3YearsAmt>523</CurrentTaxYearMinus3YearsAmt>
        <CurrentTaxYearMinus2YearsAmt>616</CurrentTaxYearMinus2YearsAmt>
        <CurrentTaxYearMinus1YearAmt>2297</CurrentTaxYearMinus1YearAmt>
        <CurrentTaxYearAmt>2295</CurrentTaxYearAmt>
        <TotalAmt>7065</TotalAmt>
      </GrossInvestmentIncome170Grp>
      <TotalSupportAmt>17355787</TotalSupportAmt>
      <GrossReceiptsRltdActivitiesAmt>308208</GrossReceiptsRltdActivitiesAmt>
      <PublicSupportCY170Pct>0.91930</PublicSupportCY170Pct>
      <PublicSupportPY170Pct>0.92920</PublicSupportPY170Pct>
      <ThirtyThrPctSuprtTestsCY170Ind>X</ThirtyThrPctSuprtTestsCY170Ind>
    </IRS990ScheduleA>
    <IRS990ScheduleB documentId="RetDoc1234500001" />
    <IRS990ScheduleD documentId="RetDoc1040000001">
      <LeaseholdImprovementsGrp>
        <OtherCostOrOtherBasisAmt>128185</OtherCostOrOtherBasisAmt>
        <DepreciationAmt>120994</DepreciationAmt>
        <BookValueAmt>7191</BookValueAmt>
      </LeaseholdImprovementsGrp>
      <EquipmentGrp>
        <OtherCostOrOtherBasisAmt>44790</OtherCostOrOtherBasisAmt>
        <DepreciationAmt>44312</DepreciationAmt>
        <BookValueAmt>478</BookValueAmt>
      </EquipmentGrp>
      <TotalBookValueLandBuildingsAmt>7669</TotalBookValueLandBuildingsAmt>
    </IRS990ScheduleD>
    <IRS990ScheduleG documentId="RetDoc1041300001">
      <FundraisingEventInformationGrp>
        <Event1Nm>CELEBRITY SPELLING BEE</Event1Nm>
        <GrossReceiptsEvent1Amt>167322</GrossReceiptsEvent1Amt>
        <CharitableContriEvent1Amt>131438</CharitableContriEvent1Amt>
        <GrossRevenueEvent1Amt>35884</GrossRevenueEvent1Amt>
        <RentFacilityCostsEvent1Amt>4034</RentFacilityCostsEvent1Amt>
        <FoodAndBeverageEvent1Amt>20904</FoodAndBeverageEvent1Amt>
        <EntertainmentEvent1Amt>6000</EntertainmentEvent1Amt>
        <OtherDirectExpensesEvent1Amt>35542</OtherDirectExpensesEvent1Amt>
        <GrossReceiptsTotalAmt>167322</GrossReceiptsTotalAmt>
        <CharitableContributionsTotAmt>131438</CharitableContributionsTotAmt>
        <GrossRevenueTotalEventsAmt>35884</GrossRevenueTotalEventsAmt>
        <RentFcltyCostsTotalEventsAmt>4034</RentFcltyCostsTotalEventsAmt>
        <FoodAndBeverageTotalEventsAmt>20904</FoodAndBeverageTotalEventsAmt>
        <EntertainmentTotalEventsAmt>6000</EntertainmentTotalEventsAmt>
        <OthDirectExpnssTotalEventsAmt>35542</OthDirectExpnssTotalEventsAmt>
        <DirectExpenseSummaryEventsAmt>66480</DirectExpenseSummaryEventsAmt>
        <NetIncomeSummaryAmt>-30596</NetIncomeSummaryAmt>
      </FundraisingEventInformationGrp>
    </IRS990ScheduleG>
    <IRS990ScheduleI documentId="RetDoc1041900001">
      <GrantRecordsMaintainedInd>1</GrantRecordsMaintainedInd>
      <RecipientTable>
        <RecipientBusinessName>
          <BusinessNameLine1Txt>PORTLAND PUBLIC SCHOOL DISTRICT</BusinessNameLine1Txt>
        </RecipientBusinessName>
        <USAddress>
          <AddressLine1Txt>501 N DIXON STREET</AddressLine1Txt>
          <CityNm>PORTLAND</CityNm>
          <StateAbbreviationCd>OR</StateAbbreviationCd>
          <ZIPCd>97227</ZIPCd>
        </USAddress>
        <RecipientEIN>936000830</RecipientEIN>
        <IRCSectionDesc>GOVERNMENT</IRCSectionDesc>
        <NonCashAssistanceAmt>1724729</NonCashAssistanceAmt>
        <ValuationMethodUsedDesc>ESTIMATED COST</ValuationMethodUsedDesc>
        <NonCashAssistanceDesc>SCHOOL CLASSROOM SUPPLIES</NonCashAssistanceDesc>
        <PurposeOfGrantTxt>SUPPORT OF SCHOOLS</PurposeOfGrantTxt>
      </RecipientTable>
      <RecipientTable>
        <RecipientBusinessName>
          <BusinessNameLine1Txt>DAVID DOUGLAS SCHOOL DISTRICT</BusinessNameLine1Txt>
        </RecipientBusinessName>
        <USAddress>
          <AddressLine1Txt>11300 NE HALSEY STREET</AddressLine1Txt>
          <CityNm>PORTLAND</CityNm>
          <StateAbbreviationCd>OR</StateAbbreviationCd>
          <ZIPCd>97220</ZIPCd>
        </USAddress>
        <RecipientEIN>936014226</RecipientEIN>
        <IRCSectionDesc>GOVERNMENT</IRCSectionDesc>
        <NonCashAssistanceAmt>480734</NonCashAssistanceAmt>
        <ValuationMethodUsedDesc>ESTIMATED COST</ValuationMethodUsedDesc>
        <NonCashAssistanceDesc>SCHOOL CLASSROOM SUPPLIES</NonCashAssistanceDesc>
        <PurposeOfGrantTxt>SUPPORT OF SCHOOLS</PurposeOfGrantTxt>
      </RecipientTable>
      <RecipientTable>
        <RecipientBusinessName>
          <BusinessNameLine1Txt>PARKROSE SCHOOL DISTRICT</BusinessNameLine1Txt>
        </RecipientBusinessName>
        <USAddress>
          <AddressLine1Txt>10636 NE PRESCOTT STREET</AddressLine1Txt>
          <CityNm>PORTLAND</CityNm>
          <StateAbbreviationCd>OR</StateAbbreviationCd>
          <ZIPCd>97220</ZIPCd>
        </USAddress>
        <RecipientEIN>936000833</RecipientEIN>
        <IRCSectionDesc>GOVERNMENT</IRCSectionDesc>
        <NonCashAssistanceAmt>119288</NonCashAssistanceAmt>
        <ValuationMethodUsedDesc>ESTIMATED COST</ValuationMethodUsedDesc>
        <NonCashAssistanceDesc>SCHOOL CLASSROOM SUPPLIES</NonCashAssistanceDesc>
        <PurposeOfGrantTxt>SUPPORT OF SCHOOLS</PurposeOfGrantTxt>
      </RecipientTable>
      <RecipientTable>
        <RecipientBusinessName>
          <BusinessNameLine1Txt>HILLSBORO SCHOOL DISTRICT</BusinessNameLine1Txt>
        </RecipientBusinessName>
        <USAddress>
          <AddressLine1Txt>3083 NE 49TH PLACE</AddressLine1Txt>
          <CityNm>HILLSBORO</CityNm>
          <StateAbbreviationCd>OR</StateAbbreviationCd>
          <ZIPCd>97124</ZIPCd>
        </USAddress>
        <RecipientEIN>911779425</RecipientEIN>
        <IRCSectionDesc>GOVERNMENT</IRCSectionDesc>
        <NonCashAssistanceAmt>71630</NonCashAssistanceAmt>
        <ValuationMethodUsedDesc>ESTIMATED COST</ValuationMethodUsedDesc>
        <NonCashAssistanceDesc>SCHOOL CLASSROOM SUPPLIES</NonCashAssistanceDesc>
        <PurposeOfGrantTxt>SUPPORT OF SCHOOLS</PurposeOfGrantTxt>
      </RecipientTable>
      <RecipientTable>
        <RecipientBusinessName>
          <BusinessNameLine1Txt>ALBINA HEAD START</BusinessNameLine1Txt>
        </RecipientBusinessName>
        <USAddress>
          <AddressLine1Txt>3417 NE 7TH AVENUE</AddressLine1Txt>
          <CityNm>PORTLAND</CityNm>
          <StateAbbreviationCd>OR</StateAbbreviationCd>
          <ZIPCd>97212</ZIPCd>
        </USAddress>
        <RecipientEIN>921069936</RecipientEIN>
        <IRCSectionDesc>GOVERNMENT</IRCSectionDesc>
        <NonCashAssistanceAmt>64667</NonCashAssistanceAmt>
        <ValuationMethodUsedDesc>ESTIMATED COST</ValuationMethodUsedDesc>
        <NonCashAssistanceDesc>SCHOOL CLASSROOM SUPPLIES</NonCashAssistanceDesc>
        <PurposeOfGrantTxt>SUPPORT OF SCHOOLS</PurposeOfGrantTxt>
      </RecipientTable>
      <RecipientTable>
        <RecipientBusinessName>
          <BusinessNameLine1Txt>REYNOLDS SCHOOL DISTRICT</BusinessNameLine1Txt>
        </RecipientBusinessName>
        <USAddress>
          <AddressLine1Txt>1204 NE 201ST AVENUE</AddressLine1Txt>
          <CityNm>FAIRVIEW</CityNm>
          <StateAbbreviationCd>OR</StateAbbreviationCd>
          <ZIPCd>97204</ZIPCd>
        </USAddress>
        <RecipientEIN>936000836</RecipientEIN>
        <IRCSectionDesc>GOVERNMENT</IRCSectionDesc>
        <NonCashAssistanceAmt>37226</NonCashAssistanceAmt>
        <ValuationMethodUsedDesc>ESTIMATED COST</ValuationMethodUsedDesc>
        <NonCashAssistanceDesc>SCHOOL CLASSROOM SUPPLIES</NonCashAssistanceDesc>
        <PurposeOfGrantTxt>SUPPORT OF SCHOOLS</PurposeOfGrantTxt>
      </RecipientTable>
      <RecipientTable>
        <RecipientBusinessName>
          <BusinessNameLine1Txt>BEAVERTON SCHOOL DISTRICT</BusinessNameLine1Txt>
        </RecipientBusinessName>
        <USAddress>
          <AddressLine1Txt>16550 SW MERLO ROAD</AddressLine1Txt>
          <CityNm>BEAVERTON</CityNm>
          <StateAbbreviationCd>OR</StateAbbreviationCd>
          <ZIPCd>97003</ZIPCd>
        </USAddress>
        <RecipientEIN>936161752</RecipientEIN>
        <IRCSectionDesc>GOVERNMENT</IRCSectionDesc>
        <NonCashAssistanceAmt>24837</NonCashAssistanceAmt>
        <ValuationMethodUsedDesc>ESTIMATED COST</ValuationMethodUsedDesc>
        <NonCashAssistanceDesc>SCHOOL CLASSROOM SUPPLIES</NonCashAssistanceDesc>
        <PurposeOfGrantTxt>SUPPORT OF SCHOOLS</PurposeOfGrantTxt>
      </RecipientTable>
      <RecipientTable>
        <RecipientBusinessName>
          <BusinessNameLine1Txt>NORTH CLACKAMAS SCHOOL DISTRICT</BusinessNameLine1Txt>
        </RecipientBusinessName>
        <USAddress>
          <AddressLine1Txt>4444 SE LAKE ROAD</AddressLine1Txt>
          <CityNm>MILWAUKIE</CityNm>
          <StateAbbreviationCd>OR</StateAbbreviationCd>
          <ZIPCd>97222</ZIPCd>
        </USAddress>
        <RecipientEIN>930599524</RecipientEIN>
        <IRCSectionDesc>GOVERNMENT</IRCSectionDesc>
        <NonCashAssistanceAmt>24320</NonCashAssistanceAmt>
        <ValuationMethodUsedDesc>ESTIMATED COST</ValuationMethodUsedDesc>
        <NonCashAssistanceDesc>SCHOOL CLASSROOM SUPPLIES</NonCashAssistanceDesc>
        <PurposeOfGrantTxt>SUPPORT OF SCHOOLS</PurposeOfGrantTxt>
      </RecipientTable>
      <RecipientTable>
        <RecipientBusinessName>
          <BusinessNameLine1Txt>OREGON CITY SCHOOL DISTRICT</BusinessNameLine1Txt>
        </RecipientBusinessName>
        <USAddress>
          <AddressLine1Txt>1417 12TH STREET</AddressLine1Txt>
          <CityNm>OREGON CITY</CityNm>
          <StateAbbreviationCd>OR</StateAbbreviationCd>
          <ZIPCd>97045</ZIPCd>
        </USAddress>
        <RecipientEIN>341691643</RecipientEIN>
        <IRCSectionDesc>GOVERNMENT</IRCSectionDesc>
        <NonCashAssistanceAmt>22308</NonCashAssistanceAmt>
        <ValuationMethodUsedDesc>ESTIMATED COST</ValuationMethodUsedDesc>
        <NonCashAssistanceDesc>SCHOOL CLASSROOM SUPPLIES</NonCashAssistanceDesc>
        <PurposeOfGrantTxt>SUPPORT OF SCHOOLS</PurposeOfGrantTxt>
      </RecipientTable>
      <RecipientTable>
        <RecipientBusinessName>
          <BusinessNameLine1Txt>CHICAGO PUBLIC SCHOOL DISTRICT</BusinessNameLine1Txt>
        </RecipientBusinessName>
        <USAddress>
          <AddressLine1Txt>42 W MADISON STREET</AddressLine1Txt>
          <CityNm>CHICAGO</CityNm>
          <StateAbbreviationCd>IL</StateAbbreviationCd>
          <ZIPCd>60602</ZIPCd>
        </USAddress>
        <RecipientEIN>364094830</RecipientEIN>
        <IRCSectionDesc>GOVERNMENT</IRCSectionDesc>
        <NonCashAssistanceAmt>12692</NonCashAssistanceAmt>
        <ValuationMethodUsedDesc>ESTIMATED COST</ValuationMethodUsedDesc>
        <NonCashAssistanceDesc>SCHOOL CLASSROOM SUPPLIES</NonCashAssistanceDesc>
        <PurposeOfGrantTxt>SUPPORT OF SCHOOLS</PurposeOfGrantTxt>
      </RecipientTable>
      <RecipientTable>
        <RecipientBusinessName>
          <BusinessNameLine1Txt>LAKE OSWEGO SCHOOL DISTRICT</BusinessNameLine1Txt>
        </RecipientBusinessName>
        <USAddress>
          <AddressLine1Txt>2455 COUNTRY CLUB ROAD</AddressLine1Txt>
          <CityNm>LAKE OSWEGO</CityNm>
          <StateAbbreviationCd>OR</StateAbbreviationCd>
          <ZIPCd>97034</ZIPCd>
        </USAddress>
        <RecipientEIN>936008560</RecipientEIN>
        <IRCSectionDesc>GOVERNMENT</IRCSectionDesc>
        <NonCashAssistanceAmt>11472</NonCashAssistanceAmt>
        <ValuationMethodUsedDesc>ESTIMATED COST</ValuationMethodUsedDesc>
        <NonCashAssistanceDesc>SCHOOL CLASSROOM SUPPLIES</NonCashAssistanceDesc>
        <PurposeOfGrantTxt>SUPPORT OF SCHOOLS</PurposeOfGrantTxt>
      </RecipientTable>
      <RecipientTable>
        <RecipientBusinessName>
          <BusinessNameLine1Txt>EVERGREEN SCHOOL DISTRICT</BusinessNameLine1Txt>
        </RecipientBusinessName>
        <USAddress>
          <AddressLine1Txt>PO BOX 8910</AddressLine1Txt>
          <CityNm>VANCOUVER</CityNm>
          <StateAbbreviationCd>WA</StateAbbreviationCd>
          <ZIPCd>98668</ZIPCd>
        </USAddress>
        <RecipientEIN>916001600</RecipientEIN>
        <IRCSectionDesc>GOVERNMENT</IRCSectionDesc>
        <NonCashAssistanceAmt>11193</NonCashAssistanceAmt>
        <ValuationMethodUsedDesc>ESTIMATED COST</ValuationMethodUsedDesc>
        <NonCashAssistanceDesc>SCHOOL CLASSROOM SUPPLIES</NonCashAssistanceDesc>
        <PurposeOfGrantTxt>SUPPORT OF SCHOOLS</PurposeOfGrantTxt>
      </RecipientTable>
      <RecipientTable>
        <RecipientBusinessName>
          <BusinessNameLine1Txt>GRESHAM BARLOW SCHOOL DISTRICT</BusinessNameLine1Txt>
        </RecipientBusinessName>
        <USAddress>
          <AddressLine1Txt>1331 NW EASTMAN PARKWAY</AddressLine1Txt>
          <CityNm>GRESHAM</CityNm>
          <StateAbbreviationCd>OR</StateAbbreviationCd>
          <ZIPCd>97030</ZIPCd>
        </USAddress>
        <RecipientEIN>936000831</RecipientEIN>
        <IRCSectionDesc>GOVERNMENT</IRCSectionDesc>
        <NonCashAssistanceAmt>10215</NonCashAssistanceAmt>
        <ValuationMethodUsedDesc>ESTIMATED COST</ValuationMethodUsedDesc>
        <NonCashAssistanceDesc>SCHOOL CLASSROOM SUPPLIES</NonCashAssistanceDesc>
        <PurposeOfGrantTxt>SUPPORT OF SCHOOLS</PurposeOfGrantTxt>
      </RecipientTable>
      <RecipientTable>
        <RecipientBusinessName>
          <BusinessNameLine1Txt>VANCOUVER PUBLIC SCHOOLS</BusinessNameLine1Txt>
        </RecipientBusinessName>
        <USAddress>
          <AddressLine1Txt>2901 FALK ROAD</AddressLine1Txt>
          <CityNm>VANCOUVER</CityNm>
          <StateAbbreviationCd>WA</StateAbbreviationCd>
          <ZIPCd>98661</ZIPCd>
        </USAddress>
        <RecipientEIN>910971800</RecipientEIN>
        <IRCSectionDesc>GOVERNMENT</IRCSectionDesc>
        <NonCashAssistanceAmt>10148</NonCashAssistanceAmt>
        <ValuationMethodUsedDesc>ESTIMATED COST</ValuationMethodUsedDesc>
        <NonCashAssistanceDesc>SCHOOL CLASSROOM SUPPLIES</NonCashAssistanceDesc>
        <PurposeOfGrantTxt>SUPPORT OF SCHOOLS</PurposeOfGrantTxt>
      </RecipientTable>
      <RecipientTable>
        <RecipientBusinessName>
          <BusinessNameLine1Txt>CENTENNIAL SCHOOL DISTRICT</BusinessNameLine1Txt>
        </RecipientBusinessName>
        <USAddress>
          <AddressLine1Txt>18135 SE BROOKLYN</AddressLine1Txt>
          <CityNm>PORTLAND</CityNm>
          <StateAbbreviationCd>OR</StateAbbreviationCd>
          <ZIPCd>97236</ZIPCd>
        </USAddress>
        <RecipientEIN>936000847</RecipientEIN>
        <IRCSectionDesc>GOVERNMENT</IRCSectionDesc>
        <NonCashAssistanceAmt>8017</NonCashAssistanceAmt>
        <ValuationMethodUsedDesc>ESTIMATED COST</ValuationMethodUsedDesc>
        <NonCashAssistanceDesc>SCHOOL CLASSROOM SUPPLIES</NonCashAssistanceDesc>
        <PurposeOfGrantTxt>SUPPORT OF SCHOOLS</PurposeOfGrantTxt>
      </RecipientTable>
      <RecipientTable>
        <RecipientBusinessName>
          <BusinessNameLine1Txt>BEND-LA PINE SCHOOL DISTRICT</BusinessNameLine1Txt>
        </RecipientBusinessName>
        <USAddress>
          <AddressLine1Txt>3030 NW ELWOOD LANE</AddressLine1Txt>
          <CityNm>BEND</CityNm>
          <StateAbbreviationCd>OR</StateAbbreviationCd>
          <ZIPCd>97703</ZIPCd>
        </USAddress>
        <RecipientEIN>936000393</RecipientEIN>
        <IRCSectionDesc>GOVERNMENT</IRCSectionDesc>
        <NonCashAssistanceAmt>6940</NonCashAssistanceAmt>
        <ValuationMethodUsedDesc>ESTIMATED COST</ValuationMethodUsedDesc>
        <NonCashAssistanceDesc>SCHOOL CLASSROOM SUPPLIES</NonCashAssistanceDesc>
        <PurposeOfGrantTxt>SUPPORT OF SCHOOLS</PurposeOfGrantTxt>
      </RecipientTable>
      <RecipientTable>
        <RecipientBusinessName>
          <BusinessNameLine1Txt>TIGARD TUALATIN SCHOOL DISTRICT</BusinessNameLine1Txt>
        </RecipientBusinessName>
        <USAddress>
          <AddressLine1Txt>6960 SW SANDBURG STREET</AddressLine1Txt>
          <CityNm>TIGARD</CityNm>
          <StateAbbreviationCd>OR</StateAbbreviationCd>
          <ZIPCd>97223</ZIPCd>
        </USAddress>
        <RecipientEIN>930572833</RecipientEIN>
        <IRCSectionDesc>GOVERNMENT</IRCSectionDesc>
        <NonCashAssistanceAmt>6169</NonCashAssistanceAmt>
        <ValuationMethodUsedDesc>ESTIMATED COST</ValuationMethodUsedDesc>
        <NonCashAssistanceDesc>SCHOOL CLASSROOM SUPPLIES</NonCashAssistanceDesc>
        <PurposeOfGrantTxt>SUPPORT OF SCHOOLS</PurposeOfGrantTxt>
      </RecipientTable>
      <RecipientTable>
        <RecipientBusinessName>
          <BusinessNameLine1Txt>HACIENDA CDC</BusinessNameLine1Txt>
        </RecipientBusinessName>
        <USAddress>
          <AddressLine1Txt>6700 NE KILLINGSWORTH STREET</AddressLine1Txt>
          <CityNm>PORTLAND</CityNm>
          <StateAbbreviationCd>OR</StateAbbreviationCd>
          <ZIPCd>97218</ZIPCd>
        </USAddress>
        <RecipientEIN>930979064</RecipientEIN>
        <IRCSectionDesc>501(C)3</IRCSectionDesc>
        <NonCashAssistanceAmt>6049</NonCashAssistanceAmt>
        <ValuationMethodUsedDesc>ESTIMATED COST</ValuationMethodUsedDesc>
        <NonCashAssistanceDesc>SCHOOL CLASSROOM SUPPLIES</NonCashAssistanceDesc>
        <PurposeOfGrantTxt>SUPPORT OF SCHOOLS</PurposeOfGrantTxt>
      </RecipientTable>
      <RecipientTable>
        <RecipientBusinessName>
          <BusinessNameLine1Txt>WEST LINN-WILSONVILLE SCHOOL DISTRICT</BusinessNameLine1Txt>
        </RecipientBusinessName>
        <USAddress>
          <AddressLine1Txt>22210 SW STAFFORD ROAD</AddressLine1Txt>
          <CityNm>TUALATIN</CityNm>
          <StateAbbreviationCd>OR</StateAbbreviationCd>
          <ZIPCd>97062</ZIPCd>
        </USAddress>
        <RecipientEIN>936000234</RecipientEIN>
        <IRCSectionDesc>GOVERNMENT</IRCSectionDesc>
        <NonCashAssistanceAmt>6015</NonCashAssistanceAmt>
        <ValuationMethodUsedDesc>ESTIMATED COST</ValuationMethodUsedDesc>
        <NonCashAssistanceDesc>SCHOOL CLASSROOM SUPPLIES</NonCashAssistanceDesc>
        <PurposeOfGrantTxt>SUPPORT OF SCHOOLS</PurposeOfGrantTxt>
      </RecipientTable>
      <RecipientTable>
        <RecipientBusinessName>
          <BusinessNameLine1Txt>SALEM-KEIZER PUBLIC SCHOOLS</BusinessNameLine1Txt>
        </RecipientBusinessName>
        <USAddress>
          <AddressLine1Txt>2450 LANCASTER DRIVE NE</AddressLine1Txt>
          <CityNm>SALEM</CityNm>
          <StateAbbreviationCd>OR</StateAbbreviationCd>
          <ZIPCd>97305</ZIPCd>
        </USAddress>
        <RecipientEIN>936000763</RecipientEIN>
        <IRCSectionDesc>GOVERNMENT</IRCSectionDesc>
        <NonCashAssistanceAmt>5458</NonCashAssistanceAmt>
        <ValuationMethodUsedDesc>ESTIMATED COST</ValuationMethodUsedDesc>
        <NonCashAssistanceDesc>SCHOOL CLASSROOM SUPPLIES</NonCashAssistanceDesc>
        <PurposeOfGrantTxt>SUPPORT OF SCHOOLS</PurposeOfGrantTxt>
      </RecipientTable>
      <RecipientTable>
        <RecipientBusinessName>
          <BusinessNameLine1Txt>MOUNT HOOD COMMUNITY COLLEGE HEAD START</BusinessNameLine1Txt>
        </RecipientBusinessName>
        <USAddress>
          <AddressLine1Txt>10100 NE PRESCOTT STREET</AddressLine1Txt>
          <CityNm>PORTLAND</CityNm>
          <StateAbbreviationCd>OR</StateAbbreviationCd>
          <ZIPCd>97220</ZIPCd>
        </USAddress>
        <RecipientEIN>930546890</RecipientEIN>
        <IRCSectionDesc>GOVERNMENT</IRCSectionDesc>
        <NonCashAssistanceAmt>5270</NonCashAssistanceAmt>
        <ValuationMethodUsedDesc>ESTIMATED COST</ValuationMethodUsedDesc>
        <NonCashAssistanceDesc>SCHOOL CLASSROOM SUPPLIES</NonCashAssistanceDesc>
        <PurposeOfGrantTxt>SUPPORT OF SCHOOLS</PurposeOfGrantTxt>
      </RecipientTable>
      <Total501c3OrgCnt>21</Total501c3OrgCnt>
      <SupplementalInformationDetail>
        <FormAndLineReferenceDesc>PART I, LINE 2:</FormAndLineReferenceDesc>
        <ExplanationTxt>EACH YEAR THE ORGANIZATION PROVIDES NON-CASH GRANTS OF SCHOOL SUPPLIES TO SCHOOLS, TEACHERS AND HOME SCHOOL FAMILIES.</ExplanationTxt>
      </SupplementalInformationDetail>
    </IRS990ScheduleI>
    <IRS990ScheduleM documentId="RetDoc1042900001">
      <OtherNonCashContriTableGrp>
        <NonCashCheckboxInd>X</NonCashCheckboxInd>
        <Desc>SUPPLIES</Desc>
        <ContributionCnt>826</ContributionCnt>
        <NoncashContributionsRptF990Amt>3345215</NoncashContributionsRptF990Amt>
        <MethodOfDeterminingRevenuesTxt>ESTIMATED FAIR VALUE</MethodOfDeterminingRevenuesTxt>
      </OtherNonCashContriTableGrp>
      <OtherNonCashContriTableGrp>
        <NonCashCheckboxInd>X</NonCashCheckboxInd>
        <Desc>AUCTION ITEMS</Desc>
        <ContributionCnt>53</ContributionCnt>
        <NoncashContributionsRptF990Amt>13450</NoncashContributionsRptF990Amt>
        <MethodOfDeterminingRevenuesTxt>ESTIMATED FAIR VALUE</MethodOfDeterminingRevenuesTxt>
      </OtherNonCashContriTableGrp>
      <OtherNonCashContriTableGrp>
        <NonCashCheckboxInd>X</NonCashCheckboxInd>
        <Desc>SPECIAL EVENT SUPPLIES</Desc>
        <ContributionCnt>4</ContributionCnt>
        <NoncashContributionsRptF990Amt>710</NoncashContributionsRptF990Amt>
        <MethodOfDeterminingRevenuesTxt>ESTIMATED FAIR VALUE</MethodOfDeterminingRevenuesTxt>
      </OtherNonCashContriTableGrp>
      <AnyPropertyThatMustBeHeldInd>0</AnyPropertyThatMustBeHeldInd>
      <ReviewProcessUnusualNCGiftsInd>0</ReviewProcessUnusualNCGiftsInd>
      <ThirdPartiesUsedInd>0</ThirdPartiesUsedInd>
      <SupplementalInformationDetail>
        <FormAndLineReferenceDesc>PART I, COLUMN (B):</FormAndLineReferenceDesc>
        <ExplanationTxt>THE NUMBER REPORTED IN COLUMN B IS THE NUMBER OF CONTRIBUTIONS RECEIVED.</ExplanationTxt>
      </SupplementalInformationDetail>
    </IRS990ScheduleM>
    <IRS990ScheduleO documentId="RetDoc1044400001">
      <SupplementalInformationDetail>
        <FormAndLineReferenceDesc>FORM 990, PART VI, SECTION B, LINE 11B</FormAndLineReferenceDesc>
        <ExplanationTxt>THE COMPLETE FORM 990 IS REVIEWED BY THE FULL BOARD OF DIRECTORS PRIOR TO ITS FILING WITH THE INTERNAL REVENUE SERVICE. THE TREASURER OF THE BOARD OF DIRECTORS, THE FULL FINANCE COMMITTEE, AND THE EXECUTIVE DIRECTOR ALL UNDERTAKE A DETAILED REVIEW OF THE FORM 990 PRIOR TO ITS PRESENTATION TO THE FULL BOARD FOR THEIR REVIEW AND COMMENT.</ExplanationTxt>
      </SupplementalInformationDetail>
      <SupplementalInformationDetail>
        <FormAndLineReferenceDesc>FORM 990, PART VI, SECTION B, LINE 12C</FormAndLineReferenceDesc>
        <ExplanationTxt>THE ORGANIZATION'S CONFLICT OF INTEREST POLICIES MANDATE AN ANNUAL DISCLOSURE OF ALL POSSIBLE CONFLICTS, AS WELL AS DISCLOSURE THROUGHOUT THE COURSE OF THE YEAR IF AND WHEN POTENTIAL CONFLICTS ARISE. AT LEAST ANNUALLY, ALL BOARD MEMBERS AND ALL KEY EMPLOYEES ARE ASKED TO CERTIFY IN WRITING THE EXISTENCE, OR LACK THEREOF, ANY CONFLICTS OF INTEREST.</ExplanationTxt>
      </SupplementalInformationDetail>
      <SupplementalInformationDetail>
        <FormAndLineReferenceDesc>FORM 990, PART VI, SECTION B, LINE 15A</FormAndLineReferenceDesc>
        <ExplanationTxt>THE EXECUTIVE DIRECTOR SUBMITS A WRITTEN SELF-EVALUATION TO THE BOARD CHAIR. THE BOARD CHAIR ALSO COMPLETES AN EVALUATION OF THE EXECUTIVE DIRECTOR'S PERFORMANCE. THIS DATA IS THEN REVIEWED BY THE EXECUTIVE COMMITTEE WITH CONSIDERATION OF HISTORICAL INCREASES TO DECIDE ON APPROPRIATE COMPENSATION. THE EXECUTIVE COMMITTEE ALSO CONSIDERS APPROPRIATE COMPARABLE DATA AND DOCUMENTS ITS PROCESS AND ALL DECISIONS REACHED.</ExplanationTxt>
      </SupplementalInformationDetail>
      <SupplementalInformationDetail>
        <FormAndLineReferenceDesc>FORM 990, PART VI, SECTION C, LINE 19</FormAndLineReferenceDesc>
        <ExplanationTxt>THE ORGANIZATION MAKES ITS GOVERNING INSTRUMENTS, CONFLICT OF INTEREST POLICIES, AND FINANCIAL STATEMENTS AVAILABLE TO THE PUBLIC UPON REQUEST.</ExplanationTxt>
      </SupplementalInformationDetail>
    </IRS990ScheduleO>
  </ReturnData>
</Return>